agentics/__init__.py
agentics/dspy_core/__init__.py
agentics/dspy_core/base.py
agentics/embedding.py
agentics/llm.py
agentics/utils.py
agentics-0.2.2.dist-info/LICENSE
agentics-0.2.2.dist-info/METADATA
agentics-0.2.2.dist-info/WHEEL
agentics-0.2.2.dist-info/RECORD
