Metadata-Version: 2.1
Name: agentics
Version: 0.2.2
Summary: A minimal LLM agent library
Author: Facundo Goiriz
Author-email: facundogoiriz@gmail.com
Requires-Python: >=3.10,<3.14
Classifier: Programming Language :: Python :: 3
Classifier: Programming Language :: Python :: 3.10
Classifier: Programming Language :: Python :: 3.11
Classifier: Programming Language :: Python :: 3.12
Classifier: Programming Language :: Python :: 3.13
Requires-Dist: dspy (>=3.0.3,<4.0.0)
Requires-Dist: numpy (>=1.26.4,<2.0.0)
Requires-Dist: openai (>=1.58.1)
Requires-Dist: pydantic (>=2.10.4)
